{
  "generatedAt": "2026-03-05T03:30:50.526Z",
  "canonicalModelId": "550e8400-e29b-41d4-a716-446655440000",
  "canonicalModelVersion": "1.0.0",
  "canonicalModelDomain": "order-management",
  "totalRulesNeedingFill": 1,
  "templates": [
    {
      "ruleId": "check-stock-on-add-item",
      "slots": [
        "action"
      ],
      "template": "templates/check-stock-on-add-item.fill-template.yaml",
      "filled": false,
      "filledAt": null,
      "filledBy": null,
      "gateResult": null
    }
  ]
}